malt/__init__.py
malt/_version.py
malt/converters/__init__.py
malt/converters/asserts.py
malt/converters/break_statements.py
malt/converters/call_trees.py
malt/converters/conditional_expressions.py
malt/converters/continue_statements.py
malt/converters/control_flow.py
malt/converters/directives.py
malt/converters/functions.py
malt/converters/lists.py
malt/converters/logical_expressions.py
malt/converters/return_statements.py
malt/converters/slices.py
malt/converters/variables.py
malt/core/__init__.py
malt/core/ag_ctx.py
malt/core/config.py
malt/core/config_lib.py
malt/core/converter.py
malt/core/unsupported_features_checker.py
malt/impl/__init__.py
malt/impl/api.py
malt/impl/conversion.py
malt/lang/__init__.py
malt/lang/directives.py
malt/lang/special_functions.py
malt/operators/__init__.py
malt/operators/conditional_expressions.py
malt/operators/control_flow.py
malt/operators/data_structures.py
malt/operators/dispatch_context.py
malt/operators/exceptions.py
malt/operators/function_wrappers.py
malt/operators/logical.py
malt/operators/py_builtins.py
malt/operators/slices.py
malt/operators/variables.py
malt/pyct/__init__.py
malt/pyct/anno.py
malt/pyct/ast_util.py
malt/pyct/cache.py
malt/pyct/cfg.py
malt/pyct/error_utils.py
malt/pyct/errors.py
malt/pyct/gast_util.py
malt/pyct/inspect_utils.py
malt/pyct/loader.py
malt/pyct/naming.py
malt/pyct/origin_info.py
malt/pyct/parser.py
malt/pyct/pretty_printer.py
malt/pyct/qual_names.py
malt/pyct/templates.py
malt/pyct/transformer.py
malt/pyct/transpiler.py
malt/pyct/common_transformers/__init__.py
malt/pyct/common_transformers/anf.py
malt/pyct/static_analysis/__init__.py
malt/pyct/static_analysis/activity.py
malt/pyct/static_analysis/annos.py
malt/pyct/static_analysis/liveness.py
malt/pyct/static_analysis/reaching_definitions.py
malt/pyct/static_analysis/reaching_fndefs.py
malt/pyct/static_analysis/type_inference.py
malt/utils/__init__.py
malt/utils/ag_logging.py
malt/utils/type_registry.py
diastatic_malt-2.15.1.dist-info/LICENSE
diastatic_malt-2.15.1.dist-info/METADATA
diastatic_malt-2.15.1.dist-info/NOTICE
diastatic_malt-2.15.1.dist-info/WHEEL
diastatic_malt-2.15.1.dist-info/top_level.txt
diastatic_malt-2.15.1.dist-info/RECORD
