Metadata-Version: 2.1
Name: diastatic-malt
Version: 2.15.1
Summary: A library for Python operator overloading
Home-page: https://github.com/PennyLaneAI/diastatic-malt
Maintainer: Xanadu Inc.
Maintainer-email: software@xanadu.ai
License: Apache License 2.0
Classifier: Natural Language :: English
Classifier: Intended Audience :: Developers
Classifier: Development Status :: 5 - Production/Stable
Classifier: License :: OSI Approved :: Apache Software License
Classifier: Programming Language :: Python :: 3
Classifier: Programming Language :: Python :: 3.9
Classifier: Programming Language :: Python :: 3.10
Classifier: Programming Language :: Python :: 3.11
Classifier: Programming Language :: Python :: 3 :: Only
Provides: malt
Requires-Python: >=3.9
License-File: LICENSE
License-File: NOTICE
Requires-Dist: astunparse
Requires-Dist: gast
Requires-Dist: termcolor
